imio.scan_logger-0.3.1-py3.11-nspkg.pth
imio/scan_logger/__init__.py
imio/scan_logger/configure.zcml
imio/scan_logger/interfaces.py
imio/scan_logger/services.py
imio/scan_logger/setuphandlers.py
imio/scan_logger/utils.py
imio/scan_logger/profiles/default/browserlayer.xml
imio/scan_logger/profiles/default/metadata.xml
imio/scan_logger/profiles/default/registry/main.xml
imio/scan_logger/profiles/uninstall/browserlayer.xml
imio.scan_logger-0.3.1.dist-info/LICENSE.GPL
imio.scan_logger-0.3.1.dist-info/LICENSE.rst
imio.scan_logger-0.3.1.dist-info/METADATA
imio.scan_logger-0.3.1.dist-info/WHEEL
imio.scan_logger-0.3.1.dist-info/entry_points.txt
imio.scan_logger-0.3.1.dist-info/namespace_packages.txt
imio.scan_logger-0.3.1.dist-info/top_level.txt
imio.scan_logger-0.3.1.dist-info/RECORD
