Metadata-Version: 2.1
Name: imio.scan_logger
Version: 0.3.1
Summary: Plone product to save log files or messages from scan clients
Home-page: https://github.com/imio/imio.scan_logger
Author: sgeulette
Author-email: s.geulette@imio.be
License: GPL version 2
Project-URL: PyPI, https://pypi.org/project/imio.scan_logger/
Project-URL: Source, https://github.com/imio/imio.scan_logger
Project-URL: Tracker, https://github.com/imio/imio.scan_logger/issues
Keywords: Python Plone CMS
Classifier: Development Status :: 5 - Production/Stable
Classifier: Environment :: Web Environment
Classifier: Framework :: Plone
Classifier: Framework :: Plone :: Addon
Classifier: Framework :: Plone :: 6.0
Classifier: Programming Language :: Python
Classifier: Programming Language :: Python :: 3.10
Classifier: Operating System :: OS Independent
Classifier: License :: OSI Approved :: GNU General Public License v2 (GPLv2)
Requires-Python: >=3.7
License-File: LICENSE.GPL
License-File: LICENSE.rst
Requires-Dist: setuptools
Requires-Dist: imio.helpers >=1.0.0rc4
Requires-Dist: plone.api >=1.8.4
Requires-Dist: plone.app.dexterity
Provides-Extra: test
Requires-Dist: plone.app.testing ; extra == 'test'
Requires-Dist: plone.testing >=5.0.0 ; extra == 'test'
Requires-Dist: plone.app.contenttypes ; extra == 'test'
Requires-Dist: plone.app.robotframework[debug] ; extra == 'test'
